<Module>
	<Name value="Custom Troop Upgrade And Replacer Mod"/>
	<Id value="CustomTroopUpgrades"/>
	<Version value="v0.5.2"/>
	<SingleplayerModule value="true"/>
	<MultiplayerModule value="false"/>
	<Official value="false"/>
	<DependedModules>
		<DependedModule Id="Native"/>
		<DependedModule Id="SandBoxCore"/>
		<DependedModule Id="Sandbox"/>
		<DependedModule Id="CustomBattle"/>
		<DependedModule Id="StoryMode"/>
	</DependedModules>
  <SubModules>
    <SubModule>
      <Name value="CustomTroopUpgrades"/>
      <DLLName value="CustomTroopUpgrades.dll"/>
      <SubModuleClassType value="CustomTroopUpgrades.CustomTroopUpgradesCore"/>
      <Tags>
        <Tag key="DedicatedServerType" value="none" />
        <Tag key="IsNoRenderModeElement" value="false" />
      </Tags>
    </SubModule>
  </SubModules>
  <Xmls></Xmls>
</Module>